{"meta":{"source":"IBGE — API de Localidades e API de Malhas","sourceUrl":"https://servicodados.ibge.gov.br/api/docs/","coordinateMethod":"Centroide do maior polígono municipal na malha de qualidade mínima","generatedAt":"2026-07-21T21:51:53.003Z","uf":"TO","total":139},"municipalities":[{"ibgeCode":"1700251","name":"Abreulândia","latitude":-9.47968,"longitude":-49.30869},{"ibgeCode":"1700301","name":"Aguiarnópolis","latitude":-6.48674,"longitude":-47.51295},{"ibgeCode":"1700350","name":"Aliança do Tocantins","latitude":-11.33232,"longitude":-48.90702},{"ibgeCode":"1700400","name":"Almas","latitude":-11.42793,"longitude":-47.21055},{"ibgeCode":"1700707","name":"Alvorada","latitude":-12.40773,"longitude":-49.11185},{"ibgeCode":"1701002","name":"Ananás","latitude":-6.23263,"longitude":-48.18546},{"ibgeCode":"1701051","name":"Angico","latitude":-6.43486,"longitude":-47.91316},{"ibgeCode":"1701101","name":"Aparecida do Rio Negro","latitude":-9.98757,"longitude":-47.99967},{"ibgeCode":"1701309","name":"Aragominas","latitude":-6.94407,"longitude":-48.63392},{"ibgeCode":"1701903","name":"Araguacema","latitude":-8.9392,"longitude":-49.50546},{"ibgeCode":"1702000","name":"Araguaçu","latitude":-12.84034,"longitude":-49.69508},{"ibgeCode":"1702109","name":"Araguaína","latitude":-7.33161,"longitude":-48.58853},{"ibgeCode":"1702158","name":"Araguanã","latitude":-6.79129,"longitude":-48.52522},{"ibgeCode":"1702208","name":"Araguatins","latitude":-5.66665,"longitude":-48.10458},{"ibgeCode":"1702307","name":"Arapoema","latitude":-7.72266,"longitude":-48.99771},{"ibgeCode":"1702406","name":"Arraias","latitude":-12.81716,"longitude":-47.04758},{"ibgeCode":"1702554","name":"Augustinópolis","latitude":-5.49523,"longitude":-47.93001},{"ibgeCode":"1702703","name":"Aurora do Tocantins","latitude":-12.64829,"longitude":-46.42985},{"ibgeCode":"1702901","name":"Axixá do Tocantins","latitude":-5.64783,"longitude":-47.76778},{"ibgeCode":"1703008","name":"Babaçulândia","latitude":-7.17433,"longitude":-47.85603},{"ibgeCode":"1703057","name":"Bandeirantes do Tocantins","latitude":-7.90567,"longitude":-48.6753},{"ibgeCode":"1703073","name":"Barra do Ouro","latitude":-7.71783,"longitude":-47.5792},{"ibgeCode":"1703107","name":"Barrolândia","latitude":-9.86798,"longitude":-48.79323},{"ibgeCode":"1703206","name":"Bernardo Sayão","latitude":-7.98248,"longitude":-48.97063},{"ibgeCode":"1703305","name":"Bom Jesus do Tocantins","latitude":-9.0124,"longitude":-47.88135},{"ibgeCode":"1703602","name":"Brasilândia do Tocantins","latitude":-8.28917,"longitude":-48.44103},{"ibgeCode":"1703701","name":"Brejinho de Nazaré","latitude":-11.03054,"longitude":-48.62639},{"ibgeCode":"1703800","name":"Buriti do Tocantins","latitude":-5.33747,"longitude":-48.13644},{"ibgeCode":"1703826","name":"Cachoeirinha","latitude":-6.09025,"longitude":-47.84066},{"ibgeCode":"1703842","name":"Campos Lindos","latitude":-8.20326,"longitude":-46.80424},{"ibgeCode":"1703867","name":"Cariri do Tocantins","latitude":-11.93449,"longitude":-49.2039},{"ibgeCode":"1703883","name":"Carmolândia","latitude":-7.04605,"longitude":-48.37312},{"ibgeCode":"1703891","name":"Carrasco Bonito","latitude":-5.3363,"longitude":-48.01098},{"ibgeCode":"1703909","name":"Caseara","latitude":-9.40241,"longitude":-49.84814},{"ibgeCode":"1704105","name":"Centenário","latitude":-9.07388,"longitude":-47.44576},{"ibgeCode":"1705102","name":"Chapada da Natividade","latitude":-11.53948,"longitude":-47.84571},{"ibgeCode":"1704600","name":"Chapada de Areia","latitude":-10.16403,"longitude":-49.19718},{"ibgeCode":"1705508","name":"Colinas do Tocantins","latitude":-8.07846,"longitude":-48.52972},{"ibgeCode":"1716703","name":"Colméia","latitude":-8.83618,"longitude":-48.74699},{"ibgeCode":"1705557","name":"Combinado","latitude":-12.8478,"longitude":-46.50221},{"ibgeCode":"1705607","name":"Conceição do Tocantins","latitude":-12.17012,"longitude":-47.30425},{"ibgeCode":"1706001","name":"Couto Magalhães","latitude":-8.43655,"longitude":-49.16254},{"ibgeCode":"1706100","name":"Cristalândia","latitude":-10.63608,"longitude":-49.31114},{"ibgeCode":"1706258","name":"Crixás do Tocantins","latitude":-11.17338,"longitude":-49.07797},{"ibgeCode":"1706506","name":"Darcinópolis","latitude":-6.76178,"longitude":-47.7682},{"ibgeCode":"1707009","name":"Dianópolis","latitude":-11.69417,"longitude":-46.79625},{"ibgeCode":"1707108","name":"Divinópolis do Tocantins","latitude":-9.69398,"longitude":-49.35601},{"ibgeCode":"1707207","name":"Dois Irmãos do Tocantins","latitude":-9.27143,"longitude":-49.06586},{"ibgeCode":"1707306","name":"Dueré","latitude":-11.4271,"longitude":-49.39107},{"ibgeCode":"1707405","name":"Esperantina","latitude":-5.32696,"longitude":-48.53972},{"ibgeCode":"1707553","name":"Fátima","latitude":-10.81018,"longitude":-48.87357},{"ibgeCode":"1707652","name":"Figueirópolis","latitude":-12.26362,"longitude":-49.28443},{"ibgeCode":"1707702","name":"Filadélfia","latitude":-7.49739,"longitude":-47.79477},{"ibgeCode":"1708205","name":"Formoso do Araguaia","latitude":-11.95844,"longitude":-50.09932},{"ibgeCode":"1708304","name":"Goianorte","latitude":-8.87374,"longitude":-49.00975},{"ibgeCode":"1709005","name":"Goiatins","latitude":-8.09333,"longitude":-47.48047},{"ibgeCode":"1709302","name":"Guaraí","latitude":-8.7295,"longitude":-48.42303},{"ibgeCode":"1709500","name":"Gurupi","latitude":-11.65146,"longitude":-48.88794},{"ibgeCode":"1709807","name":"Ipueiras","latitude":-11.1358,"longitude":-48.40404},{"ibgeCode":"1710508","name":"Itacajá","latitude":-8.57056,"longitude":-47.66918},{"ibgeCode":"1710706","name":"Itaguatins","latitude":-5.8012,"longitude":-47.59538},{"ibgeCode":"1710904","name":"Itapiratins","latitude":-8.31552,"longitude":-48.03251},{"ibgeCode":"1711100","name":"Itaporã do Tocantins","latitude":-8.45177,"longitude":-48.75267},{"ibgeCode":"1711506","name":"Jaú do Tocantins","latitude":-12.74576,"longitude":-48.64563},{"ibgeCode":"1711803","name":"Juarina","latitude":-8.13993,"longitude":-49.11051},{"ibgeCode":"1711902","name":"Lagoa da Confusão","latitude":-11.03498,"longitude":-50.1605},{"ibgeCode":"1711951","name":"Lagoa do Tocantins","latitude":-10.34353,"longitude":-47.47882},{"ibgeCode":"1712009","name":"Lajeado","latitude":-9.85273,"longitude":-48.2911},{"ibgeCode":"1712157","name":"Lavandeira","latitude":-12.8162,"longitude":-46.40748},{"ibgeCode":"1712405","name":"Lizarda","latitude":-9.5242,"longitude":-46.93858},{"ibgeCode":"1712454","name":"Luzinópolis","latitude":-6.2061,"longitude":-47.82973},{"ibgeCode":"1712504","name":"Marianópolis do Tocantins","latitude":-9.78722,"longitude":-49.69979},{"ibgeCode":"1712702","name":"Mateiros","latitude":-10.58351,"longitude":-46.50343},{"ibgeCode":"1712801","name":"Maurilândia do Tocantins","latitude":-6.02231,"longitude":-47.58969},{"ibgeCode":"1713205","name":"Miracema do Tocantins","latitude":-9.75335,"longitude":-48.55216},{"ibgeCode":"1713304","name":"Miranorte","latitude":-9.41767,"longitude":-48.68393},{"ibgeCode":"1713601","name":"Monte do Carmo","latitude":-10.74821,"longitude":-48.01718},{"ibgeCode":"1713700","name":"Monte Santo do Tocantins","latitude":-9.99943,"longitude":-49.06655},{"ibgeCode":"1713957","name":"Muricilândia","latitude":-7.00381,"longitude":-48.78684},{"ibgeCode":"1714203","name":"Natividade","latitude":-11.79704,"longitude":-47.64974},{"ibgeCode":"1714302","name":"Nazaré","latitude":-6.32945,"longitude":-47.77933},{"ibgeCode":"1714880","name":"Nova Olinda","latitude":-7.63676,"longitude":-48.36005},{"ibgeCode":"1715002","name":"Nova Rosalândia","latitude":-10.54979,"longitude":-48.97268},{"ibgeCode":"1715101","name":"Novo Acordo","latitude":-10.15442,"longitude":-47.38394},{"ibgeCode":"1715150","name":"Novo Alegre","latitude":-12.9136,"longitude":-46.56037},{"ibgeCode":"1715259","name":"Novo Jardim","latitude":-11.7787,"longitude":-46.56986},{"ibgeCode":"1715507","name":"Oliveira de Fátima","latitude":-10.67719,"longitude":-48.87806},{"ibgeCode":"1721000","name":"Palmas","latitude":-10.21986,"longitude":-48.15406},{"ibgeCode":"1715705","name":"Palmeirante","latitude":-7.88621,"longitude":-48.15717},{"ibgeCode":"1713809","name":"Palmeiras do Tocantins","latitude":-6.59986,"longitude":-47.6434},{"ibgeCode":"1715754","name":"Palmeirópolis","latitude":-13.0188,"longitude":-48.34901},{"ibgeCode":"1716109","name":"Paraíso do Tocantins","latitude":-10.21781,"longitude":-48.82772},{"ibgeCode":"1716208","name":"Paranã","latitude":-12.69698,"longitude":-47.81351},{"ibgeCode":"1716307","name":"Pau D'Arco","latitude":-7.54595,"longitude":-48.98957},{"ibgeCode":"1716505","name":"Pedro Afonso","latitude":-9.22649,"longitude":-48.03321},{"ibgeCode":"1716604","name":"Peixe","latitude":-11.99794,"longitude":-48.55651},{"ibgeCode":"1716653","name":"Pequizeiro","latitude":-8.37964,"longitude":-48.91779},{"ibgeCode":"1717008","name":"Pindorama do Tocantins","latitude":-11.15855,"longitude":-47.55856},{"ibgeCode":"1717206","name":"Piraquê","latitude":-6.73914,"longitude":-48.24034},{"ibgeCode":"1717503","name":"Pium","latitude":-10.20945,"longitude":-49.87191},{"ibgeCode":"1717800","name":"Ponte Alta do Bom Jesus","latitude":-12.05816,"longitude":-46.59341},{"ibgeCode":"1717909","name":"Ponte Alta do Tocantins","latitude":-10.748,"longitude":-47.3252},{"ibgeCode":"1718006","name":"Porto Alegre do Tocantins","latitude":-11.51278,"longitude":-47.0467},{"ibgeCode":"1718204","name":"Porto Nacional","latitude":-10.54417,"longitude":-48.49718},{"ibgeCode":"1718303","name":"Praia Norte","latitude":-5.47605,"longitude":-47.78198},{"ibgeCode":"1718402","name":"Presidente Kennedy","latitude":-8.46163,"longitude":-48.46067},{"ibgeCode":"1718451","name":"Pugmil","latitude":-10.42414,"longitude":-48.88065},{"ibgeCode":"1718501","name":"Recursolândia","latitude":-8.69798,"longitude":-47.11216},{"ibgeCode":"1718550","name":"Riachinho","latitude":-6.46079,"longitude":-48.13614},{"ibgeCode":"1718659","name":"Rio da Conceição","latitude":-11.33697,"longitude":-46.73752},{"ibgeCode":"1718709","name":"Rio dos Bois","latitude":-9.23588,"longitude":-48.45127},{"ibgeCode":"1718758","name":"Rio Sono","latitude":-9.64642,"longitude":-47.49668},{"ibgeCode":"1718808","name":"Sampaio","latitude":-5.32706,"longitude":-47.91678},{"ibgeCode":"1718840","name":"Sandolândia","latitude":-12.4017,"longitude":-49.8768},{"ibgeCode":"1718865","name":"Santa Fé do Araguaia","latitude":-7.09267,"longitude":-48.97549},{"ibgeCode":"1718881","name":"Santa Maria do Tocantins","latitude":-8.82453,"longitude":-47.84773},{"ibgeCode":"1718899","name":"Santa Rita do Tocantins","latitude":-10.97081,"longitude":-49.29572},{"ibgeCode":"1718907","name":"Santa Rosa do Tocantins","latitude":-11.3976,"longitude":-48.11065},{"ibgeCode":"1719004","name":"Santa Tereza do Tocantins","latitude":-10.29975,"longitude":-47.74209},{"ibgeCode":"1720002","name":"Santa Terezinha do Tocantins","latitude":-6.47208,"longitude":-47.74992},{"ibgeCode":"1720101","name":"São Bento do Tocantins","latitude":-5.97505,"longitude":-47.93849},{"ibgeCode":"1720150","name":"São Félix do Tocantins","latitude":-10.06778,"longitude":-46.67866},{"ibgeCode":"1720200","name":"São Miguel do Tocantins","latitude":-5.54263,"longitude":-47.59879},{"ibgeCode":"1720259","name":"São Salvador do Tocantins","latitude":-12.57933,"longitude":-48.36411},{"ibgeCode":"1720309","name":"São Sebastião do Tocantins","latitude":-5.24213,"longitude":-48.33042},{"ibgeCode":"1720499","name":"São Valério","latitude":-11.80456,"longitude":-48.1697},{"ibgeCode":"1720655","name":"Silvanópolis","latitude":-11.13109,"longitude":-48.0048},{"ibgeCode":"1720804","name":"Sítio Novo do Tocantins","latitude":-5.6365,"longitude":-47.68386},{"ibgeCode":"1720853","name":"Sucupira","latitude":-12.11371,"longitude":-48.83619},{"ibgeCode":"1708254","name":"Tabocão","latitude":-9.07143,"longitude":-48.54522},{"ibgeCode":"1720903","name":"Taguatinga","latitude":-12.38865,"longitude":-46.56514},{"ibgeCode":"1720937","name":"Taipas do Tocantins","latitude":-12.1392,"longitude":-46.9939},{"ibgeCode":"1720978","name":"Talismã","latitude":-12.68141,"longitude":-49.04889},{"ibgeCode":"1721109","name":"Tocantínia","latitude":-9.6039,"longitude":-48.14229},{"ibgeCode":"1721208","name":"Tocantinópolis","latitude":-6.25625,"longitude":-47.53786},{"ibgeCode":"1721257","name":"Tupirama","latitude":-8.93908,"longitude":-48.25967},{"ibgeCode":"1721307","name":"Tupiratins","latitude":-8.35604,"longitude":-48.20939},{"ibgeCode":"1722081","name":"Wanderlândia","latitude":-6.90868,"longitude":-48.00112},{"ibgeCode":"1722107","name":"Xambioá","latitude":-6.54576,"longitude":-48.44988}]}
